comms_sdk/__init__.py
comms_sdk/v1/__init__.py
comms_sdk/v1/comms_sdk.py
comms_sdk/v1/models.py
comms_sdk/v1/utils.py
comms_sdk-1.0.1.dist-info/METADATA
comms_sdk-1.0.1.dist-info/WHEEL
comms_sdk-1.0.1.dist-info/top_level.txt
comms_sdk-1.0.1.dist-info/RECORD
