Metadata-Version: 2.4
Name: comms_sdk
Version: 1.0.1
Summary: Comms Platform Python SDK
Author-email: Pahappa Limited <systems@pahappa.com>
License-Expression: MIT
Requires-Dist: requests
